mlpcode/__init__.py
mlpcode/activation.py
mlpcode/callbacks.py
mlpcode/cli.py
mlpcode/data/affnist/readme.txt
mlpcode/data/cifar-10/readme.txt
mlpcode/data/data_banknote_authentication.txt
mlpcode/data/fashion-mnist/readme.txt
mlpcode/data/mnist/readme.txt
mlpcode/data/mnist-c/readme.txt
mlpcode/float32_error.py
mlpcode/layers.py
mlpcode/loss.py
mlpcode/network.py
mlpcode/optim.py
mlpcode/utils.py
mlpcode/utilsNp.py
mlpcode-1.0.0.dist-info/entry_points.txt
mlpcode-1.0.0.dist-info/WHEEL
mlpcode-1.0.0.dist-info/METADATA
mlpcode-1.0.0.dist-info/RECORD
