Metadata-Version: 2.1
Name: mlpcode
Version: 1.0.0
Summary: MLP cli for semester project
License: MIT
Author: Arslan
Author-email: rslnkrmt2552@gmail.com
Requires-Python: >=3.6,<4.0
Classifier: License :: OSI Approved :: MIT License
Classifier: Programming Language :: Python :: 3
Classifier: Programming Language :: Python :: 3.6
Classifier: Programming Language :: Python :: 3.7
Classifier: Programming Language :: Python :: 3.8
Requires-Dist: cupy-cuda102 (>=7.3.0,<8.0.0)
Requires-Dist: h5py (>=2.10.0,<3.0.0)
Requires-Dist: numpy (>=1.18.2,<2.0.0)
Requires-Dist: typer (>=0.1.1,<0.2.0)
